xash/__init__.py
xash/charts/__init__.py
xash/charts/plotly.py
xash/data.py
xash-0.1.0.dist-info/LICENSE
xash-0.1.0.dist-info/WHEEL
xash-0.1.0.dist-info/METADATA
xash-0.1.0.dist-info/RECORD
